dice/__init__.py
dice/bottom.py
dice/client.py
dice/commands.py
dice/completers.py
dice/config.py
dice/data/__init__.py
dice/data/command_syntax.csv
dice/data/commands/__init__.py
dice/data/commands/_index.md
dice/data/commands/acl-cat.md
dice/data/commands/acl-deluser.md
dice/data/commands/acl-dryrun.md
dice/data/commands/acl-genpass.md
dice/data/commands/acl-getuser.md
dice/data/commands/acl-help.md
dice/data/commands/acl-list.md
dice/data/commands/acl-load.md
dice/data/commands/acl-log.md
dice/data/commands/acl-save.md
dice/data/commands/acl-setuser.md
dice/data/commands/acl-users.md
dice/data/commands/acl-whoami.md
dice/data/commands/acl.md
dice/data/commands/append.md
dice/data/commands/asking.md
dice/data/commands/auth.md
dice/data/commands/bgrewriteaof.md
dice/data/commands/bgsave.md
dice/data/commands/bitcount.md
dice/data/commands/bitfield.md
dice/data/commands/bitfield_ro.md
dice/data/commands/bitop.md
dice/data/commands/bitpos.md
dice/data/commands/blmove.md
dice/data/commands/blmpop.md
dice/data/commands/blpop.md
dice/data/commands/brpop.md
dice/data/commands/brpoplpush.md
dice/data/commands/bzmpop.md
dice/data/commands/bzpopmax.md
dice/data/commands/bzpopmin.md
dice/data/commands/client-caching.md
dice/data/commands/client-getname.md
dice/data/commands/client-getredir.md
dice/data/commands/client-help.md
dice/data/commands/client-id.md
dice/data/commands/client-info.md
dice/data/commands/client-kill.md
dice/data/commands/client-list.md
dice/data/commands/client-no-evict.md
dice/data/commands/client-pause.md
dice/data/commands/client-reply.md
dice/data/commands/client-setname.md
dice/data/commands/client-tracking.md
dice/data/commands/client-trackinginfo.md
dice/data/commands/client-unblock.md
dice/data/commands/client-unpause.md
dice/data/commands/client.md
dice/data/commands/cluster-addslots.md
dice/data/commands/cluster-addslotsrange.md
dice/data/commands/cluster-bumpepoch.md
dice/data/commands/cluster-count-failure-reports.md
dicedb_cli-0.0.2.dist-info/LICENSE
dicedb_cli-0.0.2.dist-info/METADATA
dicedb_cli-0.0.2.dist-info/WHEEL
dicedb_cli-0.0.2.dist-info/entry_points.txt
dicedb_cli-0.0.2.dist-info/RECORD
