Metadata-Version: 2.1
Name: dicedb-cli
Version: 0.0.2
Summary: A CLI for DiceDB with auto completion and syntax highlighting.
Home-page: https://github.com/dicedb/cli
License: BSD-3-Clause
Keywords: Redis,key-value store,Commandline tools,Redis Client
Author: arpitbbhayani
Requires-Python: >=3.8,<4.0
Classifier: Development Status :: 4 - Beta
Classifier: Environment :: Console
Classifier: Environment :: Console :: Curses
Classifier: Environment :: MacOS X
Classifier: Intended Audience :: Developers
Classifier: License :: OSI Approved :: BSD License
Classifier: License :: OSI Approved :: MIT License
Classifier: Operating System :: OS Independent
Classifier: Programming Language :: Python :: 3
Classifier: Programming Language :: Python :: 3.8
Classifier: Programming Language :: Python :: 3.9
Classifier: Programming Language :: Python :: 3.10
Classifier: Programming Language :: Python :: 3.11
Classifier: Programming Language :: Python :: 3.12
Classifier: Topic :: Database
Requires-Dist: Pygments (>=2,<3)
Requires-Dist: click (>=8.0,<9.0)
Requires-Dist: configobj (>=5.0,<6.0)
Requires-Dist: mistune (>=3.0,<4.0)
Requires-Dist: packaging (>=23.0,<24.0)
Requires-Dist: prompt_toolkit (>=3,<4)
Requires-Dist: python-dateutil (>=2.8.2,<3.0.0)
Requires-Dist: redis (>=5.0.0,<6.0.0)
Requires-Dist: wcwidth (==0.1.9)
Project-URL: Repository, https://github.com/dicedb/cli
